thermal_optimal_path/__init__.py
thermal_optimal_path/error_models.py
thermal_optimal_path/lattice.py
thermal_optimal_path/statistics.py
thermal_optimal_path-0.11.dist-info/METADATA
thermal_optimal_path-0.11.dist-info/RECORD
thermal_optimal_path-0.11.dist-info/WHEEL
thermal_optimal_path-0.11.dist-info/top_level.txt
